awsf3/__init__.py
awsf3/__main__.py
awsf3/aws_run_workflow_generic.sh
awsf3/cloudwatch_agent_config.json
awsf3/log.py
awsf3/spot_failure_detection.sh
awsf3/target.py
awsf3/utils.py
pyproject.toml
tibanna/__init__.py
tibanna/__main__.py
tibanna/_version.py
tibanna/ami.py
tibanna/awsem.py
tibanna/base.py
tibanna/check_task.py
tibanna/core.py
tibanna/create_ami_userdata
tibanna/cw_utils.py
tibanna/dd_utils.py
tibanna/ec2_utils.py
tibanna/exceptions.py
tibanna/iam_utils.py
tibanna/job.py
tibanna/lambdas/__init__.py
tibanna/lambdas/check_task_awsem.py
tibanna/lambdas/requirements.txt
tibanna/lambdas/run_task_awsem.py
tibanna/lambdas/update_cost_awsem.py
tibanna/nnested_array.py
tibanna/pricing_utils.py
tibanna/run_task.py
tibanna/stepfunction.py
tibanna/stepfunction_cost_updater.py
tibanna/top.py
tibanna/update_cost.py
tibanna/utils.py
tibanna/vars.py
tibanna-6.0.0.dist-info/LICENSE.txt
tibanna-6.0.0.dist-info/METADATA
tibanna-6.0.0.dist-info/WHEEL
tibanna-6.0.0.dist-info/entry_points.txt
tibanna-6.0.0.dist-info/RECORD
