Metadata-Version: 2.1
Name: tibanna
Version: 6.0.0
Summary: Tibanna runs portable pipelines (in CWL/WDL) on the AWS Cloud.
Home-page: http://github.com/4dn-dcic/tibanna
License: MIT
Keywords: tibanna
Author: 4DN-DCIC Team
Author-email: support@4dnucleome.org
Requires-Python: >=3.8,<3.13
Classifier: License :: OSI Approved :: MIT License
Classifier: Natural Language :: English
Classifier: Operating System :: POSIX :: Linux
Classifier: Programming Language :: Python :: 3
Classifier: Programming Language :: Python :: 3.8
Classifier: Programming Language :: Python :: 3.9
Classifier: Programming Language :: Python :: 3.10
Classifier: Programming Language :: Python :: 3.11
Classifier: Programming Language :: Python :: 3
Classifier: Programming Language :: Python :: 3.10
Classifier: Programming Language :: Python :: 3.11
Classifier: Programming Language :: Python :: 3.12
Classifier: Programming Language :: Python :: 3.8
Classifier: Programming Language :: Python :: 3.9
Requires-Dist: Benchmark-4dn (>=0.5.25,<0.6.0)
Requires-Dist: boto3 (>=1.34.136,<2.0.0)
Requires-Dist: botocore (>=1.34.136,<2.0.0)
Requires-Dist: python-lambda-4dn (==0.12.3)
Requires-Dist: tomlkit (>=0.11.0,<0.12.0)
Project-URL: Repository, http://github.com/4dn-dcic/tibanna.git
